aihelper_akshay1/__init__.py
aihelper_akshay1/client.py
aihelper_akshay1/utils.py
aihelper_akshay1-0.2.0.dist-info/licenses/LICENSE
aihelper_akshay1-0.2.0.dist-info/METADATA
aihelper_akshay1-0.2.0.dist-info/WHEEL
aihelper_akshay1-0.2.0.dist-info/top_level.txt
aihelper_akshay1-0.2.0.dist-info/RECORD
